Workbook

Sheet README
A1: Swish Routine (weekly pass): illustrative financial model
A2: Companion to the Swish Routine proposal. Independent candidate work, not an official Swish document.
A4: The design: a weekly breakfast pass sized above the customer's usual habit. Every meal in the pass costs ₹10 less than the menu price.
A5: Example: customer usually orders breakfast 3 times a week. Pass = 5 weekday breakfasts at ₹190 instead of ₹200. Pays ₹950 for the week, saves ₹50.
A6: Unused meals carry over to the next week or are refunded. They are never treated as income.
A8: Every number in Inputs is an ILLUSTRATIVE ASSUMPTION. None are Swish facts. Swish Finance must supply real costs before any price is approved.
A9: Colour code: blue = input you can change · black = formula · green = link to another sheet · yellow fill = key assumption to replace with real data · red cell = loses money vs no pass.
A11: Tabs:
A12: Inputs: every assumption plus the derived values (break-even discount, break-even share of lifters, cost floor).
A13: Unit Economics: one customer for one week, before vs with the pass, then 1,000 customers per week and per month.
A14: Scenarios: what happens when the customer eats 3, 4, 5 or 6 breakfasts, plus customers who should not get the pass.
A15: Pass Size: why the pass must be at least 2 meals above the customer's habit.
... A22: Cash paid upfront is NOT profit: Swish still owes the customer the meals until they are delivered.

Sheet Inputs
A1: Inputs and derived values (₹, per customer per week unless stated)
A3: Assumption | B3: Value | C3: Status / note
A4: Usual breakfasts per week before the pass (N0) | B4: 3 | C4: Illustrative. ≈13 a month; TechCrunch reports Swish top users order 10+ times a month
A5: Breakfasts in the weekly pass (N1) | B5: 5 | C5: Rule: pass = usual + 2, capped at 7
A6: Menu price per eligible basket (₹) | B6: 200 | C6: Illustrative. TechCrunch reports Swish AOV of ₹200–250
A7: Variable cost per basket: food, packing, delivery, payment (₹) | B7: 150 | C7: ILLUSTRATIVE ONLY. Finance must supply
A8: Discount per pass meal (₹) | B8: 10 | C8: The customer-facing promise: your usual, ₹10 less every time
A9: Minimum contribution per discounted basket (₹) | B9: 30 | C9: Placeholder policy. Finance to set
A10: Weeks per month | B10: 4.33 | C10: 52 ÷ 12
A11: Cohort size for illustration (subscribers) | B11: 1000 | C11: Illustration only
A12: Share of break-even discount we are willing to give | B12: 0.5 | C12: Policy: keep at least half of what the extra meals earn
A14: Derived | B14: Value | C14: How it is calculated
A15: Contribution per full-price meal (c) | B15: =B6-B7 -> 50 | C15: Price − variable cost
A16: Pass price per meal (₹) | B16: =B6-B8 -> 190 | C16: Menu price − discount
A17: Weekly pass price (₹) | B17: =B5*B16 -> 950 | C17: N1 × pass price per meal
A18: Customer saving per week (₹) | B18: =B5*B8 -> 50 | C18: N1 × discount, vs buying the same meals one by one
A19: Saving as % of menu price | B19: =B8/B6 -> 0.05
A20: Saving over 4 weeks (₹) | B20: =B18*4 -> 200 | C20: What the pass shows as 'saved this month' if used every week
A21: Saving over a year if used every week (₹) | B21: =B18*52 -> 2600 | C21: Only shown to a customer as 'if you keep it up', never as a promise
A22: Contribution per pass meal (₹) | B22: =B16-B7 -> 40
A23: Cost-floor test | B23: =IF(B22>=B9,"PASS","FAIL") -> PASS | C23: Every discounted basket must still earn at least the floor
A24: Extra breakfasts per week if the customer uses the full pass | B24: =B5-B4 -> 2 | C24: N1 − N0
A25: Break-even discount per meal (₹) | B25: =B15*B24/B5 -> 20 | C25: c × (N1 − N0) ÷ N1: above this Swish earns less even when the customer uses the full pass
A26: Recommended maximum discount per meal (₹) | B26: =B12*B25 -> 10 | C26: Policy share × break-even discount
A27: Discount within policy? | B27: =IF(B8<=B26,"YES","NO") -> YES
A28: Gain per customer who uses the full pass (₹/week) | B28: =B24*B15-B5*B8 -> 50 | C28: (N1 − N0) × c − N1 × d
A29: Cost per customer who doesn't eat more (₹/week) | B29: =-B4*B8 -> -30 | C29: Discount given on the N0 meals they would have bought anyway
A30: Break-even share of subscribers who must eat more | B30: =-B29/(B28-B29) -> 0.375 | C30: Below this share, the pass loses money overall
A31: Break-even variable cost at this discount (₹) | B31: =B6-B5*B8/B24 -> 175 | C31: Above this cost, even a full-pass customer loses money
A32: Customer's weekly spend before (₹) | B32: =B4*B6 -> 600
A33: Customer's weekly spend with the pass (₹) | B33: =B17 -> 950
A34: Effective price of each EXTRA breakfast to the customer (₹) | B34: =(B33-B32)/B24 -> 175 | C34: How the extra meals feel in money terms

Sheet Unit Economics
A1: One customer, one week: before vs with a 5-breakfast pass that is fully used
A3: Line (₹ per customer per week) | B3: Before: pays per order | C3: With weekly pass | D3: Change | E3: Note
A4: Breakfasts | B4: =Inputs!B4 -> 3 | C4: =Inputs!B5 -> 5 | D4: =C4-B4 -> 2
A5: Price per breakfast | B5: =Inputs!B6 -> 200 | C5: =Inputs!B16 -> 190 | D5: =C5-B5 -> -10 | E5: ₹10 off every pass meal
A6: Sales | B6: =B4*B5 -> 600 | C6: =C4*C5 -> 950 | D6: =C6-B6 -> 350 | E6: Recognised when each meal is delivered
A7: Variable cost | B7: =B4*Inputs!B7 -> 450 | C7: =C4*Inputs!B7 -> 750 | D7: =C7-B7 -> 300 | E7: Illustrative cost per basket
A8: Contribution before fixed costs | B8: =B6-B7 -> 150 | C8: =C6-C7 -> 200 | D8: =C8-B8 -> 50 | E8: Not profit: kitchens, tech, people and marketing are still to come
A9: Contribution per breakfast | B9: =B8/B4 -> 50 | C9: =C8/C4 -> 40 | D9: =C9-B9 -> -10
A10: Cash received upfront | B10: 0 | C10: =Inputs!B17 -> 950 | D10: =C10-B10 -> 950 | E10: Cash timing only
A11: Meals owed to the customer at the start of the week | B11: 0 | C11: =Inputs!B17 -> 950 | D11: =C11-B11 -> 950 | E11: A liability until delivered
A13: Formula check
A14: Gain = (N1 − N0) × c − N1 × d | B14: =Inputs!B28 -> 50
A15: Difference vs table (should be zero) | B15: =D8-B14 -> 0
A17: What the customer sees
A18: Your usual breakfast | B18: =Inputs!B16 -> 190 | C18: ₹190 instead of ₹200, every time
A19: You save this week | B19: =Inputs!B18 -> 50 | C19: 5 × ₹10
A20: Saved over 4 weeks if used every week | B20: =Inputs!B20 -> 200
A21: Extra spend vs your old 3-breakfast week | B21: =Inputs!B33-Inputs!B32 -> 350 | C21: Shown honestly: you spend more because you get 2 more breakfasts
A22: Effective price of each extra breakfast | B22: =Inputs!B34 -> 175
A24: 1,000 subscribers who all use the full pass
A25: Line (₹) | B25: Per week | C25: Per month (× 4.33) | D25: Note
A26: Sales | B26: =D6*Inputs!$B$11 -> 350000 | C26: =B26*Inputs!$B$10 -> 1515500
A27: Variable cost | B27: =D7*Inputs!$B$11 -> 300000 | C27: =B27*Inputs!$B$10 -> 1299000
A28: Extra contribution | B28: =D8*Inputs!$B$11 -> 50000 | C28: =B28*Inputs!$B$10 -> 216500 | D28: Best case: assumes every subscriber eats 2 more breakfasts. See Sensitivity for realistic mixes.
A29: Cash received upfront | B29: =C10*Inputs!$B$11 -> 950000 | C29: =B29*Inputs!$B$10 -> 4113500 | D29: Total cash, not change. It is owed back as meals.

Sheet Scenarios
A1: Scenarios: one customer, one week (₹)
A3: Line | B3: A. Buys 5-pass, eats 3 (no change) | C3: B. Buys 5-pass, eats 4 | D3: C. Buys 5-pass, eats 5 | E3: D. Eats 5 + 1 extra at full price | F3: E. Already eats 5, offered 5-pass (should be excluded) | G3: F. Already eats 5, offered 7-day pass, eats 7 | H3: G. Already eats 5, 7-day pass, stays at 5
A4: Pass size (breakfasts) | B4: 5 | C4: 5 | D4: 5 | E4: 5 | F4: 5 | G4: 7 | H4: 7
A5: Breakfasts actually eaten this week | B5: 3 | C5: 4 | D5: 5 | E5: 6 | F5: 5 | G5: 7 | H5: 5
A6: Breakfasts without the pass (baseline) | B6: 3 | C6: 3 | D6: 3 | E6: 3 | F6: 5 | G6: 5 | H6: 5
A7: Per customer
A8: Pass meals used | B8: =MIN(B5,B4) -> 3 | C8: =MIN(C5,C4) -> 4 | D8: =MIN(D5,D4) -> 5 | E8: =MIN(E5,E4) -> 5 | F8: =MIN(F5,F4) -> 5 | G8: =MIN(G5,G4) -> 7 | H8: =MIN(H5,H4) -> 5
A9: Extra meals bought at full price | B9: =MAX(0,B5-B4) -> 0 | C9: =MAX(0,C5-C4) -> 0 | D9: =MAX(0,D5-D4) -> 0 | E9: =MAX(0,E5-E4) -> 1 | F9: =MAX(0,F5-F4) -> 0 | G9: =MAX(0,G5-G4) -> 0 | H9: =MAX(0,H5-H4) -> 0
A10: Sales recognised this week | B10: =B8*Inputs!$B$16+B9*Inputs!$B$6 -> 570 | C10: =C8*Inputs!$B$16+C9*Inputs!$B$6 -> 760 | D10: =D8*Inputs!$B$16+D9*Inputs!$B$6 -> 950 | E10: =E8*Inputs!$B$16+E9*Inputs!$B$6 -> 1150 | F10: =F8*Inputs!$B$16+F9*Inputs!$B$6 -> 950 | G10: =G8*Inputs!$B$16+G9*Inputs!$B$6 -> 1330 | H10: =H8*Inputs!$B$16+H9*Inputs!$B$6 -> 950
A11: Discount given (₹10 × pass meals used) | B11: =B8*Inputs!$B$8 -> 30 | C11: =C8*Inputs!$B$8 -> 40 | D11: =D8*Inputs!$B$8 -> 50 | E11: =E8*Inputs!$B$8 -> 50 | F11: =F8*Inputs!$B$8 -> 50 | G11: =G8*Inputs!$B$8 -> 70 | H11: =H8*Inputs!$B$8 -> 50
A12: Variable cost | B12: =B5*Inputs!$B$7 -> 450 | C12: =C5*Inputs!$B$7 -> 600 | D12: =D5*Inputs!$B$7 -> 750 | E12: =E5*Inputs!$B$7 -> 900 | F12: =F5*Inputs!$B$7 -> 750 | G12: =G5*Inputs!$B$7 -> 1050 | H12: =H5*Inputs!$B$7 -> 750
A13: Contribution | B13: =B10-B12 -> 120 | C13: =C10-C12 -> 160 | D13: =D10-D12 -> 200 | E13: =E10-E12 -> 250 | F13: =F10-F12 -> 200 | G13: =G10-G12 -> 280 | H13: =H10-H12 -> 200
A14: Contribution without the pass | B14: =B6*Inputs!$B$15 -> 150 | C14: =C6*Inputs!$B$15 -> 150 | D14: =D6*Inputs!$B$15 -> 150 | E14: =E6*Inputs!$B$15 -> 150 | F14: =F6*Inputs!$B$15 -> 250 | G14: =G6*Inputs!$B$15 -> 250 | H14: =H6*Inputs!$B$15 -> 250
A15: EXTRA CONTRIBUTION vs no pass | B15: =B13-B14 -> -30 | C15: =C13-C14 -> 10 | D15: =D13-D14 -> 50 | E15: =E13-E14 -> 100 | F15: =F13-F14 -> -50 | G15: =G13-G14 -> 30 | H15: =H13-H14 -> -50
A16: Cash paid upfront | B16: =B4*Inputs!$B$16 -> 950 | C16: =C4*Inputs!$B$16 -> 950 | D16: =D4*Inputs!$B$16 -> 950 | E16: =E4*Inputs!$B$16 -> 950 | F16: =F4*Inputs!$B$16 -> 950 | G16: =G4*Inputs!$B$16 -> 1330 | H16: =H4*Inputs!$B$16 -> 1330
A17: Unused pass meals carried over (still owed) | B17: =(B4-B8)*Inputs!$B$16 -> 380 | C17: =(C4-C8)*Inputs!$B$16 -> 190 | D17: =(D4-D8)*Inputs!$B$16 -> 0 | E17: =(E4-E8)*Inputs!$B$16 -> 0 | F17: =(F4-F8)*Inputs!$B$16 -> 0 | G17: =(G4-G8)*Inputs!$B$16 -> 0 | H17: =(H4-H8)*Inputs!$B$16 -> 380
A18: 1,000 subscribers: extra contribution per week | B18: =B15*Inputs!$B$11 -> -30000 | C18: =C15*Inputs!$B$11 -> 10000 | D18: =D15*Inputs!$B$11 -> 50000 | E18: =E15*Inputs!$B$11 -> 100000 | F18: =F15*Inputs!$B$11 -> -50000 | G18: =G15*Inputs!$B$11 -> 30000 | H18: =H15*Inputs!$B$11 -> -50000
A19: 1,000 subscribers: extra contribution per month | B19: =B15*Inputs!$B$11*Inputs!$B$10 -> -129900 | C19: =C15*Inputs!$B$11*Inputs!$B$10 -> 43300 | D19: =D15*Inputs!$B$11*Inputs!$B$10 -> 216500 | E19: =E15*Inputs!$B$11*Inputs!$B$10 -> 433000 | F19: =F15*Inputs!$B$11*Inputs!$B$10 -> -216500 | G19: =G15*Inputs!$B$11*Inputs!$B$10 -> 129900 | H19: =H15*Inputs!$B$11*Inputs!$B$10 -> -216500
A22: How to read this:
A23: A: the customer buys the pass but keeps their old habit. Swish gives ₹10 off 3 meals it would have sold anyway: −₹30. Two meals carry over.
A24: B and C: each extra breakfast earns ₹40 after the discount. Using the full pass earns +₹50 a week.
A25: E: the pass must sit above the customer's habit. Offering a 5-pass to someone already eating 5 just costs ₹50 a week.
A26: F and G: heavy users get a 7-day pass instead. It pays if they add weekends, and costs ₹50 if they don't.
A27: Unused meals are never booked as income. Doing so would make A look profitable, which would be false.

Sheet Pass Size
A1: Why the pass must be at least 2 meals above the customer's habit (₹10 off, ₹150 cost)
A2: Extra contribution per week for a customer who uses the full pass. Rows: usual breakfasts a week. Columns: pass size. Red = loses money even when fully used.
A4: Usual per week ↓ / Pass size → | B4: 3 | C4: 4 | D4: 5 | E4: 6 | F4: 7
A5: 1 | B5: =IF(B$4<=$A5,"not offered",(B$4-$A5)*Inputs!$B$15-B$4*Inputs!$B$8) -> 70 | C5: =IF(C$4<=$A5,"not offered",(C$4-$A5)*Inputs!$B$15-C$4*Inputs!$B$8) -> 110 | D5: =IF(D$4<=$A5,"not offered",(D$4-$A5)*Inputs!$B$15-D$4*Inputs!$B$8) -> 150 | E5: =IF(E$4<=$A5,"not offered",(E$4-$A5)*Inputs!$B$15-E$4*Inputs!$B$8) -> 190 | F5: =IF(F$4<=$A5,"not offered",(F$4-$A5)*Inputs!$B$15-F$4*Inputs!$B$8) -> 230
A6: 2 | B6: =IF(B$4<=$A6,"not offered",(B$4-$A6)*Inputs!$B$15-B$4*Inputs!$B$8) -> 20 | C6: =IF(C$4<=$A6,"not offered",(C$4-$A6)*Inputs!$B$15-C$4*Inputs!$B$8) -> 60 | D6: =IF(D$4<=$A6,"not offered",(D$4-$A6)*Inputs!$B$15-D$4*Inputs!$B$8) -> 100 | E6: =IF(E$4<=$A6,"not offered",(E$4-$A6)*Inputs!$B$15-E$4*Inputs!$B$8) -> 140 | F6: =IF(F$4<=$A6,"not offered",(F$4-$A6)*Inputs!$B$15-F$4*Inputs!$B$8) -> 180
A7: 3 | B7: =IF(B$4<=$A7,"not offered",(B$4-$A7)*Inputs!$B$15-B$4*Inputs!$B$8) -> not offered | C7: =IF(C$4<=$A7,"not offered",(C$4-$A7)*Inputs!$B$15-C$4*Inputs!$B$8) -> 10 | D7: =IF(D$4<=$A7,"not offered",(D$4-$A7)*Inputs!$B$15-D$4*Inputs!$B$8) -> 50 | E7: =IF(E$4<=$A7,"not offered",(E$4-$A7)*Inputs!$B$15-E$4*Inputs!$B$8) -> 90 | F7: =IF(F$4<=$A7,"not offered",(F$4-$A7)*Inputs!$B$15-F$4*Inputs!$B$8) -> 130
A8: 4 | B8: =IF(B$4<=$A8,"not offered",(B$4-$A8)*Inputs!$B$15-B$4*Inputs!$B$8) -> not offered | C8: =IF(C$4<=$A8,"not offered",(C$4-$A8)*Inputs!$B$15-C$4*Inputs!$B$8) -> not offered | D8: =IF(D$4<=$A8,"not offered",(D$4-$A8)*Inputs!$B$15-D$4*Inputs!$B$8) -> 0 | E8: =IF(E$4<=$A8,"not offered",(E$4-$A8)*Inputs!$B$15-E$4*Inputs!$B$8) -> 40 | F8: =IF(F$4<=$A8,"not offered",(F$4-$A8)*Inputs!$B$15-F$4*Inputs!$B$8) -> 80
A9: 5 | B9: =IF(B$4<=$A9,"not offered",(B$4-$A9)*Inputs!$B$15-B$4*Inputs!$B$8) -> not offered | C9: =IF(C$4<=$A9,"not offered",(C$4-$A9)*Inputs!$B$15-C$4*Inputs!$B$8) -> not offered | D9: =IF(D$4<=$A9,"not offered",(D$4-$A9)*Inputs!$B$15-D$4*Inputs!$B$8) -> not offered | E9: =IF(E$4<=$A9,"not offered",(E$4-$A9)*Inputs!$B$15-E$4*Inputs!$B$8) -> -10 | F9: =IF(F$4<=$A9,"not offered",(F$4-$A9)*Inputs!$B$15-F$4*Inputs!$B$8) -> 30
A10: 6 | B10: =IF(B$4<=$A10,"not offered",(B$4-$A10)*Inputs!$B$15-B$4*Inputs!$B$8) -> not offered | C10: =IF(C$4<=$A10,"not offered",(C$4-$A10)*Inputs!$B$15-C$4*Inputs!$B$8) -> not offered | D10: =IF(D$4<=$A10,"not offered",(D$4-$A10)*Inputs!$B$15-D$4*Inputs!$B$8) -> not offered | E10: =IF(E$4<=$A10,"not offered",(E$4-$A10)*Inputs!$B$15-E$4*Inputs!$B$8) -> not offered | F10: =IF(F$4<=$A10,"not offered",(F$4-$A10)*Inputs!$B$15-F$4*Inputs!$B$8) -> -20
A12: Rule used in the proposal: pass size = usual + 2, capped at 7. A pass only 1 meal above habit barely pays, and one at or below habit is never offered.

Sheet Sensitivity
A1: Sensitivity: how robust is the weekly pass? (₹ per subscriber per week). Not a forecast.
A3: Table 1: extra contribution for a customer who uses the full pass. Rows: variable cost per basket. Columns: discount per meal.
A4: Variable cost ↓ / Discount per meal → | B4: 0 | C4: 5 | D4: 10 | E4: 15 | F4: 20 | G4: 25
A5: 120 | B5: =(Inputs!$B$5-Inputs!$B$4)*(Inputs!$B$6-$A5)-Inputs!$B$5*B$4 -> 160 | C5: =(Inputs!$B$5-Inputs!$B$4)*(Inputs!$B$6-$A5)-Inputs!$B$5*C$4 -> 135 | D5: =(Inputs!$B$5-Inputs!$B$4)*(Inputs!$B$6-$A5)-Inputs!$B$5*D$4 -> 110 | E5: =(Inputs!$B$5-Inputs!$B$4)*(Inputs!$B$6-$A5)-Inputs!$B$5*E$4 -> 85 | F5: =(Inputs!$B$5-Inputs!$B$4)*(Inputs!$B$6-$A5)-Inputs!$B$5*F$4 -> 60 | G5: =(Inputs!$B$5-Inputs!$B$4)*(Inputs!$B$6-$A5)-Inputs!$B$5*G$4 -> 35
A6: 130 | B6: =(Inputs!$B$5-Inputs!$B$4)*(Inputs!$B$6-$A6)-Inputs!$B$5*B$4 -> 140 | C6: =(Inputs!$B$5-Inputs!$B$4)*(Inputs!$B$6-$A6)-Inputs!$B$5*C$4 -> 115 | D6: =(Inputs!$B$5-Inputs!$B$4)*(Inputs!$B$6-$A6)-Inputs!$B$5*D$4 -> 90 | E6: =(Inputs!$B$5-Inputs!$B$4)*(Inputs!$B$6-$A6)-Inputs!$B$5*E$4 -> 65 | F6: =(Inputs!$B$5-Inputs!$B$4)*(Inputs!$B$6-$A6)-Inputs!$B$5*F$4 -> 40 | G6: =(Inputs!$B$5-Inputs!$B$4)*(Inputs!$B$6-$A6)-Inputs!$B$5*G$4 -> 15
A7: 140 | B7: =(Inputs!$B$5-Inputs!$B$4)*(Inputs!$B$6-$A7)-Inputs!$B$5*B$4 -> 120 | C7: =(Inputs!$B$5-Inputs!$B$4)*(Inputs!$B$6-$A7)-Inputs!$B$5*C$4 -> 95 | D7: =(Inputs!$B$5-Inputs!$B$4)*(Inputs!$B$6-$A7)-Inputs!$B$5*D$4 -> 70 | E7: =(Inputs!$B$5-Inputs!$B$4)*(Inputs!$B$6-$A7)-Inputs!$B$5*E$4 -> 45 | F7: =(Inputs!$B$5-Inputs!$B$4)*(Inputs!$B$6-$A7)-Inputs!$B$5*F$4 -> 20 | G7: =(Inputs!$B$5-Inputs!$B$4)*(Inputs!$B$6-$A7)-Inputs!$B$5*G$4 -> -5
A8: 150 | B8: =(Inputs!$B$5-Inputs!$B$4)*(Inputs!$B$6-$A8)-Inputs!$B$5*B$4 -> 100 | C8: =(Inputs!$B$5-Inputs!$B$4)*(Inputs!$B$6-$A8)-Inputs!$B$5*C$4 -> 75 | D8: =(Inputs!$B$5-Inputs!$B$4)*(Inputs!$B$6-$A8)-Inputs!$B$5*D$4 -> 50 | E8: =(Inputs!$B$5-Inputs!$B$4)*(Inputs!$B$6-$A8)-Inputs!$B$5*E$4 -> 25 | F8: =(Inputs!$B$5-Inputs!$B$4)*(Inputs!$B$6-$A8)-Inputs!$B$5*F$4 -> 0 | G8: =(Inputs!$B$5-Inputs!$B$4)*(Inputs!$B$6-$A8)-Inputs!$B$5*G$4 -> -25
A9: 160 | B9: =(Inputs!$B$5-Inputs!$B$4)*(Inputs!$B$6-$A9)-Inputs!$B$5*B$4 -> 80 | C9: =(Inputs!$B$5-Inputs!$B$4)*(Inputs!$B$6-$A9)-Inputs!$B$5*C$4 -> 55 | D9: =(Inputs!$B$5-Inputs!$B$4)*(Inputs!$B$6-$A9)-Inputs!$B$5*D$4 -> 30 | E9: =(Inputs!$B$5-Inputs!$B$4)*(Inputs!$B$6-$A9)-Inputs!$B$5*E$4 -> 5 | F9: =(Inputs!$B$5-Inputs!$B$4)*(Inputs!$B$6-$A9)-Inputs!$B$5*F$4 -> -20 | G9: =(Inputs!$B$5-Inputs!$B$4)*(Inputs!$B$6-$A9)-Inputs!$B$5*G$4 -> -45
A10: 170 | B10: =(Inputs!$B$5-Inputs!$B$4)*(Inputs!$B$6-$A10)-Inputs!$B$5*B$4 -> 60 | C10: =(Inputs!$B$5-Inputs!$B$4)*(Inputs!$B$6-$A10)-Inputs!$B$5*C$4 -> 35 | D10: =(Inputs!$B$5-Inputs!$B$4)*(Inputs!$B$6-$A10)-Inputs!$B$5*D$4 -> 10 | E10: =(Inputs!$B$5-Inputs!$B$4)*(Inputs!$B$6-$A10)-Inputs!$B$5*E$4 -> -15 | F10: =(Inputs!$B$5-Inputs!$B$4)*(Inputs!$B$6-$A10)-Inputs!$B$5*F$4 -> -40 | G10: =(Inputs!$B$5-Inputs!$B$4)*(Inputs!$B$6-$A10)-Inputs!$B$5*G$4 -> -65
A11: 180 | B11: =(Inputs!$B$5-Inputs!$B$4)*(Inputs!$B$6-$A11)-Inputs!$B$5*B$4 -> 40 | C11: =(Inputs!$B$5-Inputs!$B$4)*(Inputs!$B$6-$A11)-Inputs!$B$5*C$4 -> 15 | D11: =(Inputs!$B$5-Inputs!$B$4)*(Inputs!$B$6-$A11)-Inputs!$B$5*D$4 -> -10 | E11: =(Inputs!$B$5-Inputs!$B$4)*(Inputs!$B$6-$A11)-Inputs!$B$5*E$4 -> -35 | F11: =(Inputs!$B$5-Inputs!$B$4)*(Inputs!$B$6-$A11)-Inputs!$B$5*F$4 -> -60 | G11: =(Inputs!$B$5-Inputs!$B$4)*(Inputs!$B$6-$A11)-Inputs!$B$5*G$4 -> -85
A12: 190 | B12: =(Inputs!$B$5-Inputs!$B$4)*(Inputs!$B$6-$A12)-Inputs!$B$5*B$4 -> 20 | C12: =(Inputs!$B$5-Inputs!$B$4)*(Inputs!$B$6-$A12)-Inputs!$B$5*C$4 -> -5 | D12: =(Inputs!$B$5-Inputs!$B$4)*(Inputs!$B$6-$A12)-Inputs!$B$5*D$4 -> -30 | E12: =(Inputs!$B$5-Inputs!$B$4)*(Inputs!$B$6-$A12)-Inputs!$B$5*E$4 -> -55 | F12: =(Inputs!$B$5-Inputs!$B$4)*(Inputs!$B$6-$A12)-Inputs!$B$5*F$4 -> -80 | G12: =(Inputs!$B$5-Inputs!$B$4)*(Inputs!$B$6-$A12)-Inputs!$B$5*G$4 -> -105
A15: Table 2: expected extra contribution per subscriber when only some use the full pass and the rest keep their old habit (₹10 off).
A16: Variable cost ↓ / Share who eat more → | B16: 0.2 | C16: 0.3 | D16: 0.4 | E16: 0.5 | F16: 0.6 | G16: 0.8 | H16: 1
A17: 120 | B17: =B$16*((Inputs!$B$5-Inputs!$B$4)*(Inputs!$B$6-$A17)-Inputs!$B$5*Inputs!$B$8)+(1-B$16)*(-Inputs!$B$4*Inputs!$B$8) -> -2 | C17: =C$16*((Inputs!$B$5-Inputs!$B$4)*(Inputs!$B$6-$A17)-Inputs!$B$5*Inputs!$B$8)+(1-C$16)*(-Inputs!$B$4*Inputs!$B$8) -> 12 | D17: =D$16*((Inputs!$B$5-Inputs!$B$4)*(Inputs!$B$6-$A17)-Inputs!$B$5*Inputs!$B$8)+(1-D$16)*(-Inputs!$B$4*Inputs!$B$8) -> 26 | E17: =E$16*((Inputs!$B$5-Inputs!$B$4)*(Inputs!$B$6-$A17)-Inputs!$B$5*Inputs!$B$8)+(1-E$16)*(-Inputs!$B$4*Inputs!$B$8) -> 40 | F17: =F$16*((Inputs!$B$5-Inputs!$B$4)*(Inputs!$B$6-$A17)-Inputs!$B$5*Inputs!$B$8)+(1-F$16)*(-Inputs!$B$4*Inputs!$B$8) -> 54 | G17: =G$16*((Inputs!$B$5-Inputs!$B$4)*(Inputs!$B$6-$A17)-Inputs!$B$5*Inputs!$B$8)+(1-G$16)*(-Inputs!$B$4*Inputs!$B$8) -> 82 | H17: =H$16*((Inputs!$B$5-Inputs!$B$4)*(Inputs!$B$6-$A17)-Inputs!$B$5*Inputs!$B$8)+(1-H$16)*(-Inputs!$B$4*Inputs!$B$8) -> 110
A18: 130 | B18: =B$16*((Inputs!$B$5-Inputs!$B$4)*(Inputs!$B$6-$A18)-Inputs!$B$5*Inputs!$B$8)+(1-B$16)*(-Inputs!$B$4*Inputs!$B$8) -> -6 | C18: =C$16*((Inputs!$B$5-Inputs!$B$4)*(Inputs!$B$6-$A18)-Inputs!$B$5*Inputs!$B$8)+(1-C$16)*(-Inputs!$B$4*Inputs!$B$8) -> 6 | D18: =D$16*((Inputs!$B$5-Inputs!$B$4)*(Inputs!$B$6-$A18)-Inputs!$B$5*Inputs!$B$8)+(1-D$16)*(-Inputs!$B$4*Inputs!$B$8) -> 18 | E18: =E$16*((Inputs!$B$5-Inputs!$B$4)*(Inputs!$B$6-$A18)-Inputs!$B$5*Inputs!$B$8)+(1-E$16)*(-Inputs!$B$4*Inputs!$B$8) -> 30 | F18: =F$16*((Inputs!$B$5-Inputs!$B$4)*(Inputs!$B$6-$A18)-Inputs!$B$5*Inputs!$B$8)+(1-F$16)*(-Inputs!$B$4*Inputs!$B$8) -> 42 | G18: =G$16*((Inputs!$B$5-Inputs!$B$4)*(Inputs!$B$6-$A18)-Inputs!$B$5*Inputs!$B$8)+(1-G$16)*(-Inputs!$B$4*Inputs!$B$8) -> 66 | H18: =H$16*((Inputs!$B$5-Inputs!$B$4)*(Inputs!$B$6-$A18)-Inputs!$B$5*Inputs!$B$8)+(1-H$16)*(-Inputs!$B$4*Inputs!$B$8) -> 90
A19: 140 | B19: =B$16*((Inputs!$B$5-Inputs!$B$4)*(Inputs!$B$6-$A19)-Inputs!$B$5*Inputs!$B$8)+(1-B$16)*(-Inputs!$B$4*Inputs!$B$8) -> -10 | C19: =C$16*((Inputs!$B$5-Inputs!$B$4)*(Inputs!$B$6-$A19)-Inputs!$B$5*Inputs!$B$8)+(1-C$16)*(-Inputs!$B$4*Inputs!$B$8) -> 0 | D19: =D$16*((Inputs!$B$5-Inputs!$B$4)*(Inputs!$B$6-$A19)-Inputs!$B$5*Inputs!$B$8)+(1-D$16)*(-Inputs!$B$4*Inputs!$B$8) -> 10 | E19: =E$16*((Inputs!$B$5-Inputs!$B$4)*(Inputs!$B$6-$A19)-Inputs!$B$5*Inputs!$B$8)+(1-E$16)*(-Inputs!$B$4*Inputs!$B$8) -> 20 | F19: =F$16*((Inputs!$B$5-Inputs!$B$4)*(Inputs!$B$6-$A19)-Inputs!$B$5*Inputs!$B$8)+(1-F$16)*(-Inputs!$B$4*Inputs!$B$8) -> 30 | G19: =G$16*((Inputs!$B$5-Inputs!$B$4)*(Inputs!$B$6-$A19)-Inputs!$B$5*Inputs!$B$8)+(1-G$16)*(-Inputs!$B$4*Inputs!$B$8) -> 50 | H19: =H$16*((Inputs!$B$5-Inputs!$B$4)*(Inputs!$B$6-$A19)-Inputs!$B$5*Inputs!$B$8)+(1-H$16)*(-Inputs!$B$4*Inputs!$B$8) -> 70
A20: 150 | B20: =B$16*((Inputs!$B$5-Inputs!$B$4)*(Inputs!$B$6-$A20)-Inputs!$B$5*Inputs!$B$8)+(1-B$16)*(-Inputs!$B$4*Inputs!$B$8) -> -14 | C20: =C$16*((Inputs!$B$5-Inputs!$B$4)*(Inputs!$B$6-$A20)-Inputs!$B$5*Inputs!$B$8)+(1-C$16)*(-Inputs!$B$4*Inputs!$B$8) -> -6 | D20: =D$16*((Inputs!$B$5-Inputs!$B$4)*(Inputs!$B$6-$A20)-Inputs!$B$5*Inputs!$B$8)+(1-D$16)*(-Inputs!$B$4*Inputs!$B$8) -> 2 | E20: =E$16*((Inputs!$B$5-Inputs!$B$4)*(Inputs!$B$6-$A20)-Inputs!$B$5*Inputs!$B$8)+(1-E$16)*(-Inputs!$B$4*Inputs!$B$8) -> 10 | F20: =F$16*((Inputs!$B$5-Inputs!$B$4)*(Inputs!$B$6-$A20)-Inputs!$B$5*Inputs!$B$8)+(1-F$16)*(-Inputs!$B$4*Inputs!$B$8) -> 18 | G20: =G$16*((Inputs!$B$5-Inputs!$B$4)*(Inputs!$B$6-$A20)-Inputs!$B$5*Inputs!$B$8)+(1-G$16)*(-Inputs!$B$4*Inputs!$B$8) -> 34 | H20: =H$16*((Inputs!$B$5-Inputs!$B$4)*(Inputs!$B$6-$A20)-Inputs!$B$5*Inputs!$B$8)+(1-H$16)*(-Inputs!$B$4*Inputs!$B$8) -> 50
A21: 160 | B21: =B$16*((Inputs!$B$5-Inputs!$B$4)*(Inputs!$B$6-$A21)-Inputs!$B$5*Inputs!$B$8)+(1-B$16)*(-Inputs!$B$4*Inputs!$B$8) -> -18 | C21: =C$16*((Inputs!$B$5-Inputs!$B$4)*(Inputs!$B$6-$A21)-Inputs!$B$5*Inputs!$B$8)+(1-C$16)*(-Inputs!$B$4*Inputs!$B$8) -> -12 | D21: =D$16*((Inputs!$B$5-Inputs!$B$4)*(Inputs!$B$6-$A21)-Inputs!$B$5*Inputs!$B$8)+(1-D$16)*(-Inputs!$B$4*Inputs!$B$8) -> -6 | E21: =E$16*((Inputs!$B$5-Inputs!$B$4)*(Inputs!$B$6-$A21)-Inputs!$B$5*Inputs!$B$8)+(1-E$16)*(-Inputs!$B$4*Inputs!$B$8) -> 0 | F21: =F$16*((Inputs!$B$5-Inputs!$B$4)*(Inputs!$B$6-$A21)-Inputs!$B$5*Inputs!$B$8)+(1-F$16)*(-Inputs!$B$4*Inputs!$B$8) -> 6 | G21: =G$16*((Inputs!$B$5-Inputs!$B$4)*(Inputs!$B$6-$A21)-Inputs!$B$5*Inputs!$B$8)+(1-G$16)*(-Inputs!$B$4*Inputs!$B$8) -> 18 | H21: =H$16*((Inputs!$B$5-Inputs!$B$4)*(Inputs!$B$6-$A21)-Inputs!$B$5*Inputs!$B$8)+(1-H$16)*(-Inputs!$B$4*Inputs!$B$8) -> 30
A22: 170 | B22: =B$16*((Inputs!$B$5-Inputs!$B$4)*(Inputs!$B$6-$A22)-Inputs!$B$5*Inputs!$B$8)+(1-B$16)*(-Inputs!$B$4*Inputs!$B$8) -> -22 | C22: =C$16*((Inputs!$B$5-Inputs!$B$4)*(Inputs!$B$6-$A22)-Inputs!$B$5*Inputs!$B$8)+(1-C$16)*(-Inputs!$B$4*Inputs!$B$8) -> -18 | D22: =D$16*((Inputs!$B$5-Inputs!$B$4)*(Inputs!$B$6-$A22)-Inputs!$B$5*Inputs!$B$8)+(1-D$16)*(-Inputs!$B$4*Inputs!$B$8) -> -14 | E22: =E$16*((Inputs!$B$5-Inputs!$B$4)*(Inputs!$B$6-$A22)-Inputs!$B$5*Inputs!$B$8)+(1-E$16)*(-Inputs!$B$4*Inputs!$B$8) -> -10 | F22: =F$16*((Inputs!$B$5-Inputs!$B$4)*(Inputs!$B$6-$A22)-Inputs!$B$5*Inputs!$B$8)+(1-F$16)*(-Inputs!$B$4*Inputs!$B$8) -> -6 | G22: =G$16*((Inputs!$B$5-Inputs!$B$4)*(Inputs!$B$6-$A22)-Inputs!$B$5*Inputs!$B$8)+(1-G$16)*(-Inputs!$B$4*Inputs!$B$8) -> 2 | H22: =H$16*((Inputs!$B$5-Inputs!$B$4)*(Inputs!$B$6-$A22)-Inputs!$B$5*Inputs!$B$8)+(1-H$16)*(-Inputs!$B$4*Inputs!$B$8) -> 10
A23: 180 | B23: =B$16*((Inputs!$B$5-Inputs!$B$4)*(Inputs!$B$6-$A23)-Inputs!$B$5*Inputs!$B$8)+(1-B$16)*(-Inputs!$B$4*Inputs!$B$8) -> -26 | C23: =C$16*((Inputs!$B$5-Inputs!$B$4)*(Inputs!$B$6-$A23)-Inputs!$B$5*Inputs!$B$8)+(1-C$16)*(-Inputs!$B$4*Inputs!$B$8) -> -24 | D23: =D$16*((Inputs!$B$5-Inputs!$B$4)*(Inputs!$B$6-$A23)-Inputs!$B$5*Inputs!$B$8)+(1-D$16)*(-Inputs!$B$4*Inputs!$B$8) -> -22 | E23: =E$16*((Inputs!$B$5-Inputs!$B$4)*(Inputs!$B$6-$A23)-Inputs!$B$5*Inputs!$B$8)+(1-E$16)*(-Inputs!$B$4*Inputs!$B$8) -> -20 | F23: =F$16*((Inputs!$B$5-Inputs!$B$4)*(Inputs!$B$6-$A23)-Inputs!$B$5*Inputs!$B$8)+(1-F$16)*(-Inputs!$B$4*Inputs!$B$8) -> -18 | G23: =G$16*((Inputs!$B$5-Inputs!$B$4)*(Inputs!$B$6-$A23)-Inputs!$B$5*Inputs!$B$8)+(1-G$16)*(-Inputs!$B$4*Inputs!$B$8) -> -14 | H23: =H$16*((Inputs!$B$5-Inputs!$B$4)*(Inputs!$B$6-$A23)-Inputs!$B$5*Inputs!$B$8)+(1-H$16)*(-Inputs!$B$4*Inputs!$B$8) -> -10
A24: 190 | B24: =B$16*((Inputs!$B$5-Inputs!$B$4)*(Inputs!$B$6-$A24)-Inputs!$B$5*Inputs!$B$8)+(1-B$16)*(-Inputs!$B$4*Inputs!$B$8) -> -30 | C24: =C$16*((Inputs!$B$5-Inputs!$B$4)*(Inputs!$B$6-$A24)-Inputs!$B$5*Inputs!$B$8)+(1-C$16)*(-Inputs!$B$4*Inputs!$B$8) -> -30 | D24: =D$16*((Inputs!$B$5-Inputs!$B$4)*(Inputs!$B$6-$A24)-Inputs!$B$5*Inputs!$B$8)+(1-D$16)*(-Inputs!$B$4*Inputs!$B$8) -> -30 | E24: =E$16*((Inputs!$B$5-Inputs!$B$4)*(Inputs!$B$6-$A24)-Inputs!$B$5*Inputs!$B$8)+(1-E$16)*(-Inputs!$B$4*Inputs!$B$8) -> -30 | F24: =F$16*((Inputs!$B$5-Inputs!$B$4)*(Inputs!$B$6-$A24)-Inputs!$B$5*Inputs!$B$8)+(1-F$16)*(-Inputs!$B$4*Inputs!$B$8) -> -30 | G24: =G$16*((Inputs!$B$5-Inputs!$B$4)*(Inputs!$B$6-$A24)-Inputs!$B$5*Inputs!$B$8)+(1-G$16)*(-Inputs!$B$4*Inputs!$B$8) -> -30 | H24: =H$16*((Inputs!$B$5-Inputs!$B$4)*(Inputs!$B$6-$A24)-Inputs!$B$5*Inputs!$B$8)+(1-H$16)*(-Inputs!$B$4*Inputs!$B$8) -> -30
A27: Table 3: break-even share of subscribers who must eat more. Rows: discount per meal. Columns: variable cost. 'never' = loses money even if everyone eats more.
A28: Discount per meal ↓ / Variable cost → | B28: 130 | C28: 140 | D28: 150 | E28: 160 | F28: 170
A29: 5 | B29: =IF(((Inputs!$B$5-Inputs!$B$4)*(Inputs!$B$6-B$28)-Inputs!$B$5*$A29)<=0,"never",(Inputs!$B$4*$A29)/(((Inputs!$B$5-Inputs!$B$4)*(Inputs!$B$6-B$28)-Inputs!$B$5*$A29)+(Inputs!$B$4*$A29))) -> 0.11538462 | C29: =IF(((Inputs!$B$5-Inputs!$B$4)*(Inputs!$B$6-C$28)-Inputs!$B$5*$A29)<=0,"never",(Inputs!$B$4*$A29)/(((Inputs!$B$5-Inputs!$B$4)*(Inputs!$B$6-C$28)-Inputs!$B$5*$A29)+(Inputs!$B$4*$A29))) -> 0.13636364 | D29: =IF(((Inputs!$B$5-Inputs!$B$4)*(Inputs!$B$6-D$28)-Inputs!$B$5*$A29)<=0,"never",(Inputs!$B$4*$A29)/(((Inputs!$B$5-Inputs!$B$4)*(Inputs!$B$6-D$28)-Inputs!$B$5*$A29)+(Inputs!$B$4*$A29))) -> 0.16666667 | E29: =IF(((Inputs!$B$5-Inputs!$B$4)*(Inputs!$B$6-E$28)-Inputs!$B$5*$A29)<=0,"never",(Inputs!$B$4*$A29)/(((Inputs!$B$5-Inputs!$B$4)*(Inputs!$B$6-E$28)-Inputs!$B$5*$A29)+(Inputs!$B$4*$A29))) -> 0.21428571 | F29: =IF(((Inputs!$B$5-Inputs!$B$4)*(Inputs!$B$6-F$28)-Inputs!$B$5*$A29)<=0,"never",(Inputs!$B$4*$A29)/(((Inputs!$B$5-Inputs!$B$4)*(Inputs!$B$6-F$28)-Inputs!$B$5*$A29)+(Inputs!$B$4*$A29))) -> 0.3
A30: 10 | B30: =IF(((Inputs!$B$5-Inputs!$B$4)*(Inputs!$B$6-B$28)-Inputs!$B$5*$A30)<=0,"never",(Inputs!$B$4*$A30)/(((Inputs!$B$5-Inputs!$B$4)*(Inputs!$B$6-B$28)-Inputs!$B$5*$A30)+(Inputs!$B$4*$A30))) -> 0.25 | C30: =IF(((Inputs!$B$5-Inputs!$B$4)*(Inputs!$B$6-C$28)-Inputs!$B$5*$A30)<=0,"never",(Inputs!$B$4*$A30)/(((Inputs!$B$5-Inputs!$B$4)*(Inputs!$B$6-C$28)-Inputs!$B$5*$A30)+(Inputs!$B$4*$A30))) -> 0.3 | D30: =IF(((Inputs!$B$5-Inputs!$B$4)*(Inputs!$B$6-D$28)-Inputs!$B$5*$A30)<=0,"never",(Inputs!$B$4*$A30)/(((Inputs!$B$5-Inputs!$B$4)*(Inputs!$B$6-D$28)-Inputs!$B$5*$A30)+(Inputs!$B$4*$A30))) -> 0.375 | E30: =IF(((Inputs!$B$5-Inputs!$B$4)*(Inputs!$B$6-E$28)-Inputs!$B$5*$A30)<=0,"never",(Inputs!$B$4*$A30)/(((Inputs!$B$5-Inputs!$B$4)*(Inputs!$B$6-E$28)-Inputs!$B$5*$A30)+(Inputs!$B$4*$A30))) -> 0.5 | F30: =IF(((Inputs!$B$5-Inputs!$B$4)*(Inputs!$B$6-F$28)-Inputs!$B$5*$A30)<=0,"never",(Inputs!$B$4*$A30)/(((Inputs!$B$5-Inputs!$B$4)*(Inputs!$B$6-F$28)-Inputs!$B$5*$A30)+(Inputs!$B$4*$A30))) -> 0.75
A31: 15 | B31: =IF(((Inputs!$B$5-Inputs!$B$4)*(Inputs!$B$6-B$28)-Inputs!$B$5*$A31)<=0,"never",(Inputs!$B$4*$A31)/(((Inputs!$B$5-Inputs!$B$4)*(Inputs!$B$6-B$28)-Inputs!$B$5*$A31)+(Inputs!$B$4*$A31))) -> 0.40909091 | C31: =IF(((Inputs!$B$5-Inputs!$B$4)*(Inputs!$B$6-C$28)-Inputs!$B$5*$A31)<=0,"never",(Inputs!$B$4*$A31)/(((Inputs!$B$5-Inputs!$B$4)*(Inputs!$B$6-C$28)-Inputs!$B$5*$A31)+(Inputs!$B$4*$A31))) -> 0.5 | D31: =IF(((Inputs!$B$5-Inputs!$B$4)*(Inputs!$B$6-D$28)-Inputs!$B$5*$A31)<=0,"never",(Inputs!$B$4*$A31)/(((Inputs!$B$5-Inputs!$B$4)*(Inputs!$B$6-D$28)-Inputs!$B$5*$A31)+(Inputs!$B$4*$A31))) -> 0.64285714 | E31: =IF(((Inputs!$B$5-Inputs!$B$4)*(Inputs!$B$6-E$28)-Inputs!$B$5*$A31)<=0,"never",(Inputs!$B$4*$A31)/(((Inputs!$B$5-Inputs!$B$4)*(Inputs!$B$6-E$28)-Inputs!$B$5*$A31)+(Inputs!$B$4*$A31))) -> 0.9 | F31: =IF(((Inputs!$B$5-Inputs!$B$4)*(Inputs!$B$6-F$28)-Inputs!$B$5*$A31)<=0,"never",(Inputs!$B$4*$A31)/(((Inputs!$B$5-Inputs!$B$4)*(Inputs!$B$6-F$28)-Inputs!$B$5*$A31)+(Inputs!$B$4*$A31))) -> never
A32: 20 | B32: =IF(((Inputs!$B$5-Inputs!$B$4)*(Inputs!$B$6-B$28)-Inputs!$B$5*$A32)<=0,"never",(Inputs!$B$4*$A32)/(((Inputs!$B$5-Inputs!$B$4)*(Inputs!$B$6-B$28)-Inputs!$B$5*$A32)+(Inputs!$B$4*$A32))) -> 0.6 | C32: =IF(((Inputs!$B$5-Inputs!$B$4)*(Inputs!$B$6-C$28)-Inputs!$B$5*$A32)<=0,"never",(Inputs!$B$4*$A32)/(((Inputs!$B$5-Inputs!$B$4)*(Inputs!$B$6-C$28)-Inputs!$B$5*$A32)+(Inputs!$B$4*$A32))) -> 0.75 | D32: =IF(((Inputs!$B$5-Inputs!$B$4)*(Inputs!$B$6-D$28)-Inputs!$B$5*$A32)<=0,"never",(Inputs!$B$4*$A32)/(((Inputs!$B$5-Inputs!$B$4)*(Inputs!$B$6-D$28)-Inputs!$B$5*$A32)+(Inputs!$B$4*$A32))) -> never | E32: =IF(((Inputs!$B$5-Inputs!$B$4)*(Inputs!$B$6-E$28)-Inputs!$B$5*$A32)<=0,"never",(Inputs!$B$4*$A32)/(((Inputs!$B$5-Inputs!$B$4)*(Inputs!$B$6-E$28)-Inputs!$B$5*$A32)+(Inputs!$B$4*$A32))) -> never | F32: =IF(((Inputs!$B$5-Inputs!$B$4)*(Inputs!$B$6-F$28)-Inputs!$B$5*$A32)<=0,"never",(Inputs!$B$4*$A32)/(((Inputs!$B$5-Inputs!$B$4)*(Inputs!$B$6-F$28)-Inputs!$B$5*$A32)+(Inputs!$B$4*$A32))) -> never
A35: Table 4: 1,000 ELIGIBLE customers, extra contribution per month (₹). Rows: share who buy the pass. Columns: share of buyers who eat more.
A36: Take-up ↓ / Share of buyers who eat more → | B36: 0.3 | C36: 0.4 | D36: 0.5 | E36: 0.6 | F36: 0.8
A37: 0.05 | B37: =Inputs!$B$11*$A37*(B$36*Inputs!$B$28+(1-B$36)*Inputs!$B$29)*Inputs!$B$10 -> -1299 | C37: =Inputs!$B$11*$A37*(C$36*Inputs!$B$28+(1-C$36)*Inputs!$B$29)*Inputs!$B$10 -> 433 | D37: =Inputs!$B$11*$A37*(D$36*Inputs!$B$28+(1-D$36)*Inputs!$B$29)*Inputs!$B$10 -> 2165 | E37: =Inputs!$B$11*$A37*(E$36*Inputs!$B$28+(1-E$36)*Inputs!$B$29)*Inputs!$B$10 -> 3897 | F37: =Inputs!$B$11*$A37*(F$36*Inputs!$B$28+(1-F$36)*Inputs!$B$29)*Inputs!$B$10 -> 7361
A38: 0.1 | B38: =Inputs!$B$11*$A38*(B$36*Inputs!$B$28+(1-B$36)*Inputs!$B$29)*Inputs!$B$10 -> -2598 | C38: =Inputs!$B$11*$A38*(C$36*Inputs!$B$28+(1-C$36)*Inputs!$B$29)*Inputs!$B$10 -> 866 | D38: =Inputs!$B$11*$A38*(D$36*Inputs!$B$28+(1-D$36)*Inputs!$B$29)*Inputs!$B$10 -> 4330 | E38: =Inputs!$B$11*$A38*(E$36*Inputs!$B$28+(1-E$36)*Inputs!$B$29)*Inputs!$B$10 -> 7794 | F38: =Inputs!$B$11*$A38*(F$36*Inputs!$B$28+(1-F$36)*Inputs!$B$29)*Inputs!$B$10 -> 14722
A39: 0.15 | B39: =Inputs!$B$11*$A39*(B$36*Inputs!$B$28+(1-B$36)*Inputs!$B$29)*Inputs!$B$10 -> -3897 | C39: =Inputs!$B$11*$A39*(C$36*Inputs!$B$28+(1-C$36)*Inputs!$B$29)*Inputs!$B$10 -> 1299 | D39: =Inputs!$B$11*$A39*(D$36*Inputs!$B$28+(1-D$36)*Inputs!$B$29)*Inputs!$B$10 -> 6495 | E39: =Inputs!$B$11*$A39*(E$36*Inputs!$B$28+(1-E$36)*Inputs!$B$29)*Inputs!$B$10 -> 11691 | F39: =Inputs!$B$11*$A39*(F$36*Inputs!$B$28+(1-F$36)*Inputs!$B$29)*Inputs!$B$10 -> 22083
A40: 0.2 | B40: =Inputs!$B$11*$A40*(B$36*Inputs!$B$28+(1-B$36)*Inputs!$B$29)*Inputs!$B$10 -> -5196 | C40: =Inputs!$B$11*$A40*(C$36*Inputs!$B$28+(1-C$36)*Inputs!$B$29)*Inputs!$B$10 -> 1732 | D40: =Inputs!$B$11*$A40*(D$36*Inputs!$B$28+(1-D$36)*Inputs!$B$29)*Inputs!$B$10 -> 8660 | E40: =Inputs!$B$11*$A40*(E$36*Inputs!$B$28+(1-E$36)*Inputs!$B$29)*Inputs!$B$10 -> 15588 | F40: =Inputs!$B$11*$A40*(F$36*Inputs!$B$28+(1-F$36)*Inputs!$B$29)*Inputs!$B$10 -> 29444
A41: 0.3 | B41: =Inputs!$B$11*$A41*(B$36*Inputs!$B$28+(1-B$36)*Inputs!$B$29)*Inputs!$B$10 -> -7794 | C41: =Inputs!$B$11*$A41*(C$36*Inputs!$B$28+(1-C$36)*Inputs!$B$29)*Inputs!$B$10 -> 2598 | D41: =Inputs!$B$11*$A41*(D$36*Inputs!$B$28+(1-D$36)*Inputs!$B$29)*Inputs!$B$10 -> 12990 | E41: =Inputs!$B$11*$A41*(E$36*Inputs!$B$28+(1-E$36)*Inputs!$B$29)*Inputs!$B$10 -> 23382 | F41: =Inputs!$B$11*$A41*(F$36*Inputs!$B$28+(1-F$36)*Inputs!$B$29)*Inputs!$B$10 -> 44166

Sheet Cost Floor
A1: Cost floor: every discounted basket must still earn at least the floor after ₹10 off
A2: Baskets are INVENTED for illustration. Real list, prices and costs must come from Swish Finance and Operations.
A3: Discount per meal (₹) | B3: =Inputs!B8 -> 10
A4: Minimum contribution (₹) | B4: =Inputs!B9 -> 30
A6: Illustrative basket | B6: Menu price (₹) | C6: Variable cost (₹) | D6: Contribution at menu price (₹) | E6: Pass price (₹) | F6: Contribution at pass price (₹) | G6: Floor test | H6: In the pass?
A7: Cold coffee + poha | B7: 200 | C7: 150 | D7: =B7-C7 -> 50 | E7: =B7-$B$3 -> 190 | F7: =E7-C7 -> 40 | G7: =IF(F7>=$B$4,"PASS","FAIL") -> PASS | H7: =IF(G7="PASS","Yes","No: sold at menu price, outside the pass") -> Yes
A8: Masala chai + veg sandwich | B8: 180 | C8: 128 | D8: =B8-C8 -> 52 | E8: =B8-$B$3 -> 170 | F8: =E8-C8 -> 42 | G8: =IF(F8>=$B$4,"PASS","FAIL") -> PASS | H8: =IF(G8="PASS","Yes","No: sold at menu price, outside the pass") -> Yes
A9: Mini idli + filter coffee | B9: 200 | C9: 155 | D9: =B9-C9 -> 45 | E9: =B9-$B$3 -> 190 | F9: =E9-C9 -> 35 | G9: =IF(F9>=$B$4,"PASS","FAIL") -> PASS | H9: =IF(G9="PASS","Yes","No: sold at menu price, outside the pass") -> Yes
A10: Rice bowl + cold drink | B10: 250 | C10: 215 | D10: =B10-C10 -> 35 | E10: =B10-$B$3 -> 240 | F10: =E10-C10 -> 25 | G10: =IF(F10>=$B$4,"PASS","FAIL") -> FAIL | H10: =IF(G10="PASS","Yes","No: sold at menu price, outside the pass") -> No: sold at menu price, outside the pass
A11: Paneer wrap + coffee | B11: 260 | C11: 205 | D11: =B11-C11 -> 55 | E11: =B11-$B$3 -> 250 | F11: =E11-C11 -> 45 | G11: =IF(F11>=$B$4,"PASS","FAIL") -> PASS | H11: =IF(G11="PASS","Yes","No: sold at menu price, outside the pass") -> Yes

Sheet Pilot Power
A1: Pilot sizing: eligible customers per group to detect the change in weekly orders
A2: All inputs are placeholders for Swish's data team. The outcome measured is breakfasts per customer per week, averaged over the 6-week test.
A4: Std deviation of a customer's weekly breakfasts, averaged over 6 weeks (assumed) | B4: 1.5
A5: Share of variance explained by pre-period orders (R², assumed) | B5: 0.5
A6: Effective std deviation after adjustment | B6: =B4*SQRT(1-B5) -> 1.0606602
A7: z for 5% two-sided significance | B7: 1.96
A8: z for 80% power | B8: 0.84
A9: Share of offered customers who buy the pass (assumed) | B9: 0.15
A10: Share of buyers who eat more (assumed) | B10: 0.5
A11: Extra breakfasts per week for those who eat more | B11: =Inputs!B24 -> 2
A12: Expected change per OFFERED customer (breakfasts/week) | B12: =B9*B10*B11 -> 0.15
A13: Eligible customers needed per group | B13: =2*((B7+B8)*B6/B12)^2 -> 784
A14: Total for two groups (holdout + pass) | B14: =2*B13 -> 1568
A16: Smallest detectable change by group size
A17: Eligible customers per group | B17: Detectable change (breakfasts/week per offered customer) | C17: As % of expected change
A18: 500 | B18: =($B$7+$B$8)*$B$6*SQRT(2/A18) -> 0.18782971 | C18: =B18/$B$12 -> 1.2521981
A19: 1000 | B19: =($B$7+$B$8)*$B$6*SQRT(2/A19) -> 0.13281566 | C19: =B19/$B$12 -> 0.88543774
A20: 1500 | B20: =($B$7+$B$8)*$B$6*SQRT(2/A20) -> 0.10844353 | C20: =B20/$B$12 -> 0.72295689
A21: 2000 | B21: =($B$7+$B$8)*$B$6*SQRT(2/A21) -> 0.093914855 | C21: =B21/$B$12 -> 0.62609903
A22: 3000 | B22: =($B$7+$B$8)*$B$6*SQRT(2/A22) -> 0.076681158 | C22: =B22/$B$12 -> 0.51120772
A23: 5000 | B23: =($B$7+$B$8)*$B$6*SQRT(2/A23) -> 0.05939697 | C23: =B23/$B$12 -> 0.3959798
A25: Below 100% = the group is big enough to see the expected effect. Judge the pilot on this holdout comparison, never on sign-ups or prepaid cash.

Sheet Facts vs Assumptions
A1: What is publicly sourced vs assumed
A3: Item | B3: Status | C3: Detail | D3: Source / owner
A4: Swish owns kitchens, sourcing and delivery | B4: Verified (company claim) | C4: No third-party restaurants | D4: justswish.in
A5: ~20,000 orders/day (Mar 2026); AOV ₹200–250; top users >10 orders/month | B5: Verified (reported) | C5: From CEO interview | D5: TechCrunch, 23 Mar 2026
A6: Monthly orders >1 million, tripled since March; lunch and dinner now largest occasions | B6: Verified (reported) | C6: With $24M round | D6: Entrepreneur India, 11 Sep 2026
A7: App has a 'Swish wallet' for referral credit; 50% off first order + free cold coffee | B7: Observed | C7: Play Store screenshots, viewed 25 Oct 2026 | D7: Google Play listing
A8: India bans 13 named dark patterns incl. false urgency, subscription trap, confirm shaming, drip pricing | B8: Verified (secondary) | C8: CCPA Guidelines notified 30 Nov 2023 | D8: JSA law firm summary
A9: Recurring auto-debits need a pre-debit alert ≥24h before; mandates can be cancelled any time; ≤₹15,000 without OTP | B9: Verified (secondary) | C9: RBI e-mandate framework; check the RBI circular before launch | D9: Outlook Business summary
A10: Who funds Zomato's subscription discounts | B10: NOT KNOWN | C10: Not assumed | D10: —
A11: ₹200 basket, ₹150 cost, 3 → 5 breakfasts a week, ₹10 off | B11: ASSUMPTION | C11: Illustrative | D11: Swish Finance must replace
A12: Take-up, share who eat more, order variance | B12: ASSUMPTION | C12: Placeholders for pilot design | D12: Swish data team
